marshenum/__init__.py
marshenum/enum_field.py
marshenum/marsh_schema.py
marshenum/model.py
marshenum-0.1.5.dist-info/METADATA
marshenum-0.1.5.dist-info/WHEEL
marshenum-0.1.5.dist-info/dependency_links.txt
marshenum-0.1.5.dist-info/top_level.txt
marshenum-0.1.5.dist-info/RECORD
